mirai/__init__.py
mirai/application.py
mirai/depend.py
mirai/exceptions.py
mirai/face.py
mirai/file.py
mirai/image.py
mirai/logger.py
mirai/misc.py
mirai/network.py
mirai/protocol.py
mirai/voice.py
mirai/entities/__init__.py
mirai/entities/builtins.py
mirai/entities/friend.py
mirai/entities/group.py
mirai/event/__init__.py
mirai/event/builtins.py
mirai/event/enums.py
mirai/event/external/__init__.py
mirai/event/external/enums.py
mirai/event/message/__init__.py
mirai/event/message/base.py
mirai/event/message/chain.py
mirai/event/message/components.py
mirai/event/message/models.py
mirai/utilles/__init__.py
mirai/utilles/dependencies.py
kuriyama_lxnet-1.3.0.dist-info/LICENSE
kuriyama_lxnet-1.3.0.dist-info/METADATA
kuriyama_lxnet-1.3.0.dist-info/WHEEL
kuriyama_lxnet-1.3.0.dist-info/top_level.txt
kuriyama_lxnet-1.3.0.dist-info/RECORD
