Metadata-Version: 2.1
Name: kuriyama-lxnet
Version: 1.3.0
Summary: A framework for OICQ(QQ, made by Tencent) headless client "Mirai".
Home-page: https://github.com/NatriumLab/python-mirai
Author: lxnet
Author-email: personnpc@gmail.com
License: UNKNOWN
Keywords: oicq qq qqbot
Platform: UNKNOWN
Classifier: Development Status :: 4 - Beta
Classifier: Intended Audience :: Developers
Classifier: Topic :: Software Development :: User Interfaces
Classifier: License :: OSI Approved :: MIT License
Classifier: Programming Language :: Python :: 3.7
Classifier: Operating System :: OS Independent
Requires-Python: >=3.7
Requires-Dist: aiohttp
Requires-Dist: pydantic
Requires-Dist: Logbook
Requires-Dist: async-lru
